[
  {
    "full_name": "facebookexperimental/reverie",
    "stargazers_count": 150,
    "open_issues_count": 2,
    "forks_count": 8
  },
  {
    "full_name": "jsoref/fwupd",
    "stargazers_count": 1,
    "open_issues_count": 0,
    "forks_count": 1
  },
  {
    "full_name": "vlang/v",
    "stargazers_count": 31180,
    "open_issues_count": 782,
    "forks_count": 1916
  },
  {
    "full_name": "LucasRufo/helm-kube-demo-app",
    "stargazers_count": 2,
    "open_issues_count": 0,
    "forks_count": 0
  },
  {
    "full_name": "google/comprehensive-rust",
    "stargazers_count": 6694,
    "open_issues_count": 27,
    "forks_count": 300
  },
  {
    "full_name": "denoland/deno_lint",
    "stargazers_count": 1284,
    "open_issues_count": 81,
    "forks_count": 139
  },
  {
    "full_name": "mattbullen/rust-steganography",
    "stargazers_count": 3,
    "open_issues_count": 0,
    "forks_count": 0
  },
  {
    "full_name": "rustdesk/rustdesk",
    "stargazers_count": 36146,
    "open_issues_count": 346,
    "forks_count": 3236
  },
  {
    "full_name": "kamiyaa/joshuto",
    "stargazers_count": 1088,
    "open_issues_count": 28,
    "forks_count": 61
  },
  {
    "full_name": "microsoft/PowerToys",
    "stargazers_count": 84891,
    "open_issues_count": 4098,
    "forks_count": 4896
  },
  {
    "full_name": "containerd/accelerated-container-image",
    "stargazers_count": 272,
    "open_issues_count": 11,
    "forks_count": 53
  },
  {
    "full_name": "rust-windowing/winit",
    "stargazers_count": 3122,
    "open_issues_count": 445,
    "forks_count": 669
  },
  {
    "full_name": "ErickWendel/myownnode",
    "stargazers_count": 118,
    "open_issues_count": 0,
    "forks_count": 5
  },
  {
    "full_name": "servo/html5ever",
    "stargazers_count": 1682,
    "open_issues_count": 51,
    "forks_count": 199
  },
  {
    "full_name": "JSextonn/rust-challenges",
    "stargazers_count": 26,
    "open_issues_count": 0,
    "forks_count": 3
  },
  {
    "full_name": "servo/servo",
    "stargazers_count": 22198,
    "open_issues_count": 3517,
    "forks_count": 2663
  },
  {
    "full_name": "trickster0/OffensiveRust",
    "stargazers_count": 1725,
    "open_issues_count": 1,
    "forks_count": 187
  },
  {
    "full_name": "dtolnay/async-trait",
    "stargazers_count": 1338,
    "open_issues_count": 5,
    "forks_count": 63
  },
  {
    "full_name": "peeeuzin/brasilapi-rs",
    "stargazers_count": 8,
    "open_issues_count": 0,
    "forks_count": 2
  },
  {
    "full_name": "nuta/kerla",
    "stargazers_count": 3160,
    "open_issues_count": 24,
    "forks_count": 80
  },
  {
    "full_name": "ahkarami/Deep-Learning-in-Production",
    "stargazers_count": 3918,
    "open_issues_count": 8,
    "forks_count": 645
  },
  {
    "full_name": "zv/SICP-guile",
    "stargazers_count": 611,
    "open_issues_count": 1,
    "forks_count": 45
  },
  {
    "full_name": "total-typescript/beginners-typescript-tutorial",
    "stargazers_count": 6991,
    "open_issues_count": 4,
    "forks_count": 831
  },
  {
    "full_name": "IceWhaleTech/CasaOS",
    "stargazers_count": 8249,
    "open_issues_count": 148,
    "forks_count": 550
  },
  {
    "full_name": "novuhq/novu",
    "stargazers_count": 17666,
    "open_issues_count": 188,
    "forks_count": 1075
  },
  {
    "full_name": "total-typescript/typescript-generics-workshop",
    "stargazers_count": 1124,
    "open_issues_count": 4,
    "forks_count": 116
  },
  {
    "full_name": "SeleniumHQ/selenium",
    "stargazers_count": 25596,
    "open_issues_count": 156,
    "forks_count": 7350
  },
  {
    "full_name": "penpot/penpot",
    "stargazers_count": 19852,
    "open_issues_count": 274,
    "forks_count": 906
  },
  {
    "full_name": "public-apis/public-apis",
    "stargazers_count": 225122,
    "open_issues_count": 125,
    "forks_count": 25646
  },
  {
    "full_name": "strapi/strapi",
    "stargazers_count": 51334,
    "open_issues_count": 410,
    "forks_count": 6226
  }
]