[
  {
    "full_name": "zv/SICP-guile",
    "stargazers_count": 592,
    "open_issues_count": 1,
    "forks_count": 44
  },
  {
    "full_name": "total-typescript/beginners-typescript-tutorial",
    "stargazers_count": 6594,
    "open_issues_count": 2,
    "forks_count": 682
  },
  {
    "full_name": "IceWhaleTech/CasaOS",
    "stargazers_count": 6830,
    "open_issues_count": 107,
    "forks_count": 438
  },
  {
    "full_name": "novuhq/novu",
    "stargazers_count": 10844,
    "open_issues_count": 128,
    "forks_count": 673
  },
  {
    "full_name": "total-typescript/typescript-generics-workshop",
    "stargazers_count": 1014,
    "open_issues_count": 1,
    "forks_count": 70
  },
  {
    "full_name": "SeleniumHQ/selenium",
    "stargazers_count": 24921,
    "open_issues_count": 111,
    "forks_count": 7219
  },
  {
    "full_name": "penpot/penpot",
    "stargazers_count": 18917,
    "open_issues_count": 235,
    "forks_count": 854
  },
  {
    "full_name": "public-apis/public-apis",
    "stargazers_count": 212713,
    "open_issues_count": 61,
    "forks_count": 24313
  },
  {
    "full_name": "strapi/strapi",
    "stargazers_count": 48875,
    "open_issues_count": 436,
    "forks_count": 5977
  },
  {
    "full_name": "Quramy/type-dungeon",
    "stargazers_count": 28,
    "open_issues_count": 7,
    "forks_count": 2
  },
  {
    "full_name": "lunatic-solutions/submillisecond",
    "stargazers_count": 637,
    "open_issues_count": 4,
    "forks_count": 12
  },
  {
    "full_name": "lyst/lightfm",
    "stargazers_count": 4155,
    "open_issues_count": 125,
    "forks_count": 651
  },
  {
    "full_name": "asciinema/agg",
    "stargazers_count": 331,
    "open_issues_count": 7,
    "forks_count": 4
  },
  {
    "full_name": "cypress-io/cypress",
    "stargazers_count": 41246,
    "open_issues_count": 2831,
    "forks_count": 2584
  },
  {
    "full_name": "sindresorhus/file-type",
    "stargazers_count": 2789,
    "open_issues_count": 16,
    "forks_count": 289
  },
  {
    "full_name": "curquiza/meilisearch-changelog-generator-gha",
    "stargazers_count": 2,
    "open_issues_count": 1,
    "forks_count": 0
  },
  {
    "full_name": "peggyjs/peggy",
    "stargazers_count": 409,
    "open_issues_count": 38,
    "forks_count": 30
  },
  {
    "full_name": "jsoref/nix",
    "stargazers_count": 1,
    "open_issues_count": 0,
    "forks_count": 1
  },
  {
    "full_name": "jsoref/pantry",
    "stargazers_count": 1,
    "open_issues_count": 0,
    "forks_count": 1
  },
  {
    "full_name": "nodejs/next-10",
    "stargazers_count": 377,
    "open_issues_count": 23,
    "forks_count": 20
  },
  {
    "full_name": "markets/awesome-ruby",
    "stargazers_count": 12462,
    "open_issues_count": 8,
    "forks_count": 1713
  },
  {
    "full_name": "berthubert/googerteller",
    "stargazers_count": 1987,
    "open_issues_count": 16,
    "forks_count": 102
  },
  {
    "full_name": "sveltejs/svelte",
    "stargazers_count": 62774,
    "open_issues_count": 794,
    "forks_count": 3067
  },
  {
    "full_name": "goldbergyoni/nodebestpractices",
    "stargazers_count": 82375,
    "open_issues_count": 35,
    "forks_count": 8527
  },
  {
    "full_name": "xsburg/vscode-javascript-booster",
    "stargazers_count": 135,
    "open_issues_count": 21,
    "forks_count": 12
  },
  {
    "full_name": "probablykasper/kadium",
    "stargazers_count": 64,
    "open_issues_count": 6,
    "forks_count": 3
  },
  {
    "full_name": "tauri-apps/tauri-action",
    "stargazers_count": 289,
    "open_issues_count": 25,
    "forks_count": 56
  },
  {
    "full_name": "quick-lint/quick-lint-js",
    "stargazers_count": 691,
    "open_issues_count": 297,
    "forks_count": 127
  },
  {
    "full_name": "MatthewSmit/AcornSharp",
    "stargazers_count": 2,
    "open_issues_count": 0,
    "forks_count": 0
  },
  {
    "full_name": "acuminous/yadda",
    "stargazers_count": 417,
    "open_issues_count": 16,
    "forks_count": 84
  }
]