[
  {
    "full_name": "karpathy/nanochat",
    "stargazers_count": 31697,
    "open_issues_count": 87,
    "forks_count": 3402
  },
  {
    "full_name": "danielmiessler/Personal_AI_Infrastructure",
    "stargazers_count": 482,
    "open_issues_count": 7,
    "forks_count": 95
  },
  {
    "full_name": "angiejones/mcp-selenium",
    "stargazers_count": 277,
    "open_issues_count": 15,
    "forks_count": 77
  },
  {
    "full_name": "microrealestate/microrealestate",
    "stargazers_count": 903,
    "open_issues_count": 24,
    "forks_count": 332
  },
  {
    "full_name": "nuxt/awesome",
    "stargazers_count": 5411,
    "open_issues_count": 19,
    "forks_count": 583
  },
  {
    "full_name": "ItzCrazyKns/Perplexica",
    "stargazers_count": 26918,
    "open_issues_count": 205,
    "forks_count": 2780
  },
  {
    "full_name": "netdata/netdata",
    "stargazers_count": 76465,
    "open_issues_count": 238,
    "forks_count": 6207
  },
  {
    "full_name": "AbacatePay/abacate-chat",
    "stargazers_count": 45,
    "open_issues_count": 7,
    "forks_count": 14
  },
  {
    "full_name": "MudBlazor/MudBlazor",
    "stargazers_count": 9751,
    "open_issues_count": 1349,
    "forks_count": 1534
  },
  {
    "full_name": "live-codes/livecodes",
    "stargazers_count": 1197,
    "open_issues_count": 27,
    "forks_count": 191
  },
  {
    "full_name": "microsoft/playwright-mcp",
    "stargazers_count": 22325,
    "open_issues_count": 31,
    "forks_count": 1779
  },
  {
    "full_name": "mbaragiola/hijos",
    "stargazers_count": 3,
    "open_issues_count": 0,
    "forks_count": 1
  },
  {
    "full_name": "bob-reis/OSINT",
    "stargazers_count": 25,
    "open_issues_count": 0,
    "forks_count": 8
  },
  {
    "full_name": "alainm23/planify",
    "stargazers_count": 4586,
    "open_issues_count": 141,
    "forks_count": 259
  },
  {
    "full_name": "plenaryapp/awesome-rss-feeds",
    "stargazers_count": 1612,
    "open_issues_count": 15,
    "forks_count": 120
  },
  {
    "full_name": "makerkit/nextjs-saas-starter-kit-lite",
    "stargazers_count": 304,
    "open_issues_count": 2,
    "forks_count": 108
  },
  {
    "full_name": "TibixDev/winboat",
    "stargazers_count": 13325,
    "open_issues_count": 151,
    "forks_count": 333
  },
  {
    "full_name": "quests-org/quests",
    "stargazers_count": 328,
    "open_issues_count": 3,
    "forks_count": 58
  },
  {
    "full_name": "bytebot-ai/bytebot",
    "stargazers_count": 9195,
    "open_issues_count": 50,
    "forks_count": 1116
  },
  {
    "full_name": "rowboatlabs/rowboat",
    "stargazers_count": 3836,
    "open_issues_count": 50,
    "forks_count": 342
  },
  {
    "full_name": "garrylachman/ElectroCRUD",
    "stargazers_count": 1547,
    "open_issues_count": 12,
    "forks_count": 311
  },
  {
    "full_name": "microsoft/BASIC-M6502",
    "stargazers_count": 4239,
    "open_issues_count": 0,
    "forks_count": 473
  },
  {
    "full_name": "github/spec-kit",
    "stargazers_count": 41236,
    "open_issues_count": 367,
    "forks_count": 3520
  },
  {
    "full_name": "laravel/boost",
    "stargazers_count": 2730,
    "open_issues_count": 41,
    "forks_count": 175
  },
  {
    "full_name": "f1db/f1db",
    "stargazers_count": 409,
    "open_issues_count": 5,
    "forks_count": 41
  },
  {
    "full_name": "coleam00/Archon",
    "stargazers_count": 12979,
    "open_issues_count": 117,
    "forks_count": 2231
  },
  {
    "full_name": "formulahendry/mcp-server-spec-driven-development",
    "stargazers_count": 359,
    "open_issues_count": 4,
    "forks_count": 29
  },
  {
    "full_name": "gurnec/btcrecover",
    "stargazers_count": 1478,
    "open_issues_count": 383,
    "forks_count": 827
  },
  {
    "full_name": "naimo84/awesome-nodered",
    "stargazers_count": 514,
    "open_issues_count": 0,
    "forks_count": 29
  },
  {
    "full_name": "jpdias/node-red-contrib-self-healing",
    "stargazers_count": 39,
    "open_issues_count": 0,
    "forks_count": 4
  }
]